stcc_triage/__init__.py
stcc_triage/api/__init__.py
stcc_triage/api/app.py
stcc_triage/api/models.py
stcc_triage/cli/__init__.py
stcc_triage/cli/api.py
stcc_triage/cli/optimize.py
stcc_triage/cli/parse.py
stcc_triage/cli/ui.py
stcc_triage/core/__init__.py
stcc_triage/core/agent.py
stcc_triage/core/paths.py
stcc_triage/core/settings.py
stcc_triage/core/signatures.py
stcc_triage/data/protocols.json
stcc_triage/data/protocols/STCC-chinese/Abdominal_Pain_Adult.md
stcc_triage/data/protocols/STCC-chinese/Abdominal_Pain_Child.md
stcc_triage/data/protocols/STCC-chinese/Abdominal_Swelling.md
stcc_triage/data/protocols/STCC-chinese/Abrasions.md
stcc_triage/data/protocols/STCC-chinese/Alcohol_Problems.md
stcc_triage/data/protocols/STCC-chinese/Allergic_Reaction.md
stcc_triage/data/protocols/STCC-chinese/Altered_Mental_Status_AMS.md
stcc_triage/data/protocols/STCC-chinese/Ankle_Injury.md
stcc_triage/data/protocols/STCC-chinese/Ankle_Problems.md
stcc_triage/data/protocols/STCC-chinese/Anxiety.md
stcc_triage/data/protocols/STCC-chinese/Appetite_Loss_Adult.md
stcc_triage/data/protocols/STCC-chinese/Appetite_Loss_Child.md
stcc_triage/data/protocols/STCC-chinese/Arm_or_Hand_Problems.md
stcc_triage/data/protocols/STCC-chinese/Arthritis_Problems.md
stcc_triage/data/protocols/STCC-chinese/Asthma.md
stcc_triage/data/protocols/STCC-chinese/Avian_Influenza_“Bird_Flu”_Exposure.md
stcc_triage/data/protocols/STCC-chinese/BackNeck_Injury.md
stcc_triage/data/protocols/STCC-chinese/Back_Pain.md
stcc_triage/data/protocols/STCC-chinese/Bad_Breath.md
stcc_triage/data/protocols/STCC-chinese/Bed-Wetting.md
stcc_triage/data/protocols/STCC-chinese/Bedbug_Exposure_or_Concerns.md
stcc_triage/data/protocols/STCC-chinese/Bee_Stings.md
stcc_triage/data/protocols/STCC-chinese/Bites_AnimalHuman.md
stcc_triage/data/protocols/STCC-chinese/Bites_Insect.md
stcc_triage/data/protocols/STCC-chinese/Bites_Marine_Animal.md
stcc_triage/data/protocols/STCC-chinese/Bites_Snake.md
dspy_stcc_homecare-2.0.1.dist-info/METADATA
dspy_stcc_homecare-2.0.1.dist-info/WHEEL
dspy_stcc_homecare-2.0.1.dist-info/entry_points.txt
dspy_stcc_homecare-2.0.1.dist-info/licenses/LICENSE
dspy_stcc_homecare-2.0.1.dist-info/RECORD
