Metadata-Version: 2.4
Name: dspy-stcc-homecare
Version: 2.0.1
Summary: DSPy extension for STCC medical triage with specialized nurses
Project-URL: Homepage, https://github.com/chenhaodev/dspy-stcc-homecare
Project-URL: Repository, https://github.com/chenhaodev/dspy-stcc-homecare
Project-URL: Documentation, https://github.com/chenhaodev/dspy-stcc-homecare#readme
Project-URL: Issues, https://github.com/chenhaodev/dspy-stcc-homecare/issues
Author: STCC Triage Agent Contributors
License: MIT
License-File: LICENSE
Keywords: ai,deepseek,dspy,healthcare,medical,stcc,triage
Classifier: Development Status :: 4 - Beta
Classifier: Intended Audience :: Healthcare Industry
Classifier: Intended Audience :: Science/Research
Classifier: License :: OSI Approved :: MIT License
Classifier: Programming Language :: Python :: 3
Classifier: Programming Language :: Python :: 3.11
Classifier: Programming Language :: Python :: 3.12
Classifier: Topic :: Scientific/Engineering :: Artificial Intelligence
Classifier: Topic :: Scientific/Engineering :: Medical Science Apps.
Requires-Python: >=3.11
Requires-Dist: dspy-ai>=2.5.0
Requires-Dist: openai>=1.0.0
Requires-Dist: pydantic-settings>=2.0.0
Requires-Dist: pydantic>=2.0.0
Requires-Dist: python-dotenv>=1.0.0
Requires-Dist: streamlit>=1.31.0
Provides-Extra: api
Requires-Dist: fastapi>=0.100.0; extra == 'api'
Requires-Dist: uvicorn>=0.20.0; extra == 'api'
Provides-Extra: dev
Requires-Dist: mypy>=1.0.0; extra == 'dev'
Requires-Dist: pytest-cov>=4.0.0; extra == 'dev'
Requires-Dist: pytest>=8.0.0; extra == 'dev'
Requires-Dist: ruff>=0.1.0; extra == 'dev'
